{
    "availableLanguageIds": [
        "en_US"
    ],
    "defaultLanguageId": "en_US",
    "fields": [
        {
            "label": {
                "en_US": "Title"
            },
            "predefinedValue": {
                "en_US": ""
            },
            "style": {
                "en_US": ""
            },
            "tip": {
                "en_US": ""
            },
            "dataType": "string",
            "indexType": "keyword",
            "localizable": true,
            "name": "Title",
            "readOnly": false,
            "repeatable": false,
            "required": false,
            "showLabel": true,
            "type": "text"
        },
        {
            "label": {
                "en_US": "Description"
            },
            "predefinedValue": {
                "en_US": ""
            },
            "style": {
                "en_US": ""
            },
            "tip": {
                "en_US": ""
            },
            "dataType": "string",
            "indexType": "keyword",
            "localizable": true,
            "name": "Description",
            "readOnly": false,
            "repeatable": false,
            "required": false,
            "showLabel": true,
            "type": "textarea"
        },
        {
            "label": {
                "en_US": "Team1"
            },
            "predefinedValue": {
                "en_US": ""
            },
            "style": {
                "en_US": ""
            },
            "tip": {
                "en_US": ""
            },
            "dataType": "string",
            "indexType": "keyword",
            "localizable": true,
            "name": "Team1",
            "readOnly": false,
            "repeatable": false,
            "required": false,
            "showLabel": true,
            "type": "text",
            "nestedFields": [
                {
                    "label": {
                        "en_US": "Image1"
                    },
                    "predefinedValue": {
                        "en_US": ""
                    },
                    "style": {
                        "en_US": ""
                    },
                    "tip": {
                        "en_US": ""
                    },
                    "dataType": "document-library",
                    "fieldNamespace": "ddm",
                    "indexType": "keyword",
                    "localizable": true,
                    "name": "Image1",
                    "readOnly": false,
                    "repeatable": false,
                    "required": false,
                    "showLabel": true,
                    "type": "ddm-documentlibrary"
                },
                {
                    "label": {
                        "en_US": "Job Title1"
                    },
                    "predefinedValue": {
                        "en_US": ""
                    },
                    "style": {
                        "en_US": ""
                    },
                    "tip": {
                        "en_US": ""
                    },
                    "dataType": "string",
                    "indexType": "keyword",
                    "localizable": true,
                    "name": "Job_Title1",
                    "readOnly": false,
                    "repeatable": false,
                    "required": false,
                    "showLabel": true,
                    "type": "text"
                },
                {
                    "label": {
                        "en_US": "Job Description1"
                    },
                    "predefinedValue": {
                        "en_US": ""
                    },
                    "style": {
                        "en_US": ""
                    },
                    "tip": {
                        "en_US": ""
                    },
                    "dataType": "string",
                    "indexType": "keyword",
                    "localizable": true,
                    "name": "Job_Description1",
                    "readOnly": false,
                    "repeatable": false,
                    "required": false,
                    "showLabel": true,
                    "type": "textarea",
                    "nestedFields": [
                        {
                            "label": {
                                "en_US": "Facebook Link1"
                            },
                            "predefinedValue": {
                                "en_US": ""
                            },
                            "style": {
                                "en_US": ""
                            },
                            "tip": {
                                "en_US": ""
                            },
                            "dataType": "string",
                            "indexType": "keyword",
                            "localizable": true,
                            "name": "Facebook_Link1",
                            "readOnly": false,
                            "repeatable": false,
                            "required": false,
                            "showLabel": true,
                            "type": "text"
                        },
                        {
                            "label": {
                                "en_US": "Twitter Link1"
                            },
                            "predefinedValue": {
                                "en_US": ""
                            },
                            "style": {
                                "en_US": ""
                            },
                            "tip": {
                                "en_US": ""
                            },
                            "dataType": "string",
                            "indexType": "keyword",
                            "localizable": true,
                            "name": "Twitter_Link1",
                            "readOnly": false,
                            "repeatable": false,
                            "required": false,
                            "showLabel": true,
                            "type": "text"
                        },
                        {
                            "label": {
                                "en_US": "Linked in Link1"
                            },
                            "predefinedValue": {
                                "en_US": ""
                            },
                            "style": {
                                "en_US": ""
                            },
                            "tip": {
                                "en_US": ""
                            },
                            "dataType": "string",
                            "indexType": "keyword",
                            "localizable": true,
                            "name": "Linked_in_Link1",
                            "readOnly": false,
                            "repeatable": false,
                            "required": false,
                            "showLabel": true,
                            "type": "text"
                        }
                    ]
                },
                {
                    "label": {
                        "en_US": "Show Facebook Link1"
                    },
                    "predefinedValue": {
                        "en_US": false
                    },
                    "style": {
                        "en_US": ""
                    },
                    "tip": {
                        "en_US": ""
                    },
                    "dataType": "boolean",
                    "indexType": "keyword",
                    "localizable": true,
                    "name": "Show_Facebook_Link1",
                    "readOnly": false,
                    "repeatable": false,
                    "required": false,
                    "showLabel": true,
                    "type": "checkbox"
                },
                {
                    "label": {
                        "en_US": "Show Twitter Link1"
                    },
                    "predefinedValue": {
                        "en_US": false
                    },
                    "style": {
                        "en_US": ""
                    },
                    "tip": {
                        "en_US": ""
                    },
                    "dataType": "boolean",
                    "indexType": "keyword",
                    "localizable": true,
                    "name": "Show_Twitter_Link1",
                    "readOnly": false,
                    "repeatable": false,
                    "required": false,
                    "showLabel": true,
                    "type": "checkbox"
                },
                {
                    "label": {
                        "en_US": "Show Linked in Link1"
                    },
                    "predefinedValue": {
                        "en_US": false
                    },
                    "style": {
                        "en_US": ""
                    },
                    "tip": {
                        "en_US": ""
                    },
                    "dataType": "boolean",
                    "indexType": "keyword",
                    "localizable": true,
                    "name": "Show_Linkedin_Link1",
                    "readOnly": false,
                    "repeatable": false,
                    "required": false,
                    "showLabel": true,
                    "type": "checkbox"
                }
            ]
        },
        {
            "label": {
                "en_US": "Team2"
            },
            "predefinedValue": {
                "en_US": ""
            },
            "style": {
                "en_US": ""
            },
            "tip": {
                "en_US": ""
            },
            "dataType": "string",
            "indexType": "keyword",
            "localizable": true,
            "name": "Team2",
            "readOnly": false,
            "repeatable": false,
            "required": false,
            "showLabel": true,
            "type": "text",
            "nestedFields": [
                {
                    "label": {
                        "en_US": "Image2"
                    },
                    "predefinedValue": {
                        "en_US": ""
                    },
                    "style": {
                        "en_US": ""
                    },
                    "tip": {
                        "en_US": ""
                    },
                    "dataType": "document-library",
                    "fieldNamespace": "ddm",
                    "indexType": "keyword",
                    "localizable": true,
                    "name": "Image2",
                    "readOnly": false,
                    "repeatable": false,
                    "required": false,
                    "showLabel": true,
                    "type": "ddm-documentlibrary"
                },
                {
                    "label": {
                        "en_US": "Job Title2"
                    },
                    "predefinedValue": {
                        "en_US": ""
                    },
                    "style": {
                        "en_US": ""
                    },
                    "tip": {
                        "en_US": ""
                    },
                    "dataType": "string",
                    "indexType": "keyword",
                    "localizable": true,
                    "name": "Job_Title2",
                    "readOnly": false,
                    "repeatable": false,
                    "required": false,
                    "showLabel": true,
                    "type": "text"
                },
                {
                    "label": {
                        "en_US": "Job Description2"
                    },
                    "predefinedValue": {
                        "en_US": ""
                    },
                    "style": {
                        "en_US": ""
                    },
                    "tip": {
                        "en_US": ""
                    },
                    "dataType": "string",
                    "indexType": "keyword",
                    "localizable": true,
                    "name": "Job_Description2",
                    "readOnly": false,
                    "repeatable": false,
                    "required": false,
                    "showLabel": true,
                    "type": "textarea",
                    "nestedFields": [
                        {
                            "label": {
                                "en_US": "Facebook Link2"
                            },
                            "predefinedValue": {
                                "en_US": ""
                            },
                            "style": {
                                "en_US": ""
                            },
                            "tip": {
                                "en_US": ""
                            },
                            "dataType": "string",
                            "indexType": "keyword",
                            "localizable": true,
                            "name": "Facebook_Link2",
                            "readOnly": false,
                            "repeatable": false,
                            "required": false,
                            "showLabel": true,
                            "type": "text"
                        },
                        {
                            "label": {
                                "en_US": "Twitter Link2"
                            },
                            "predefinedValue": {
                                "en_US": ""
                            },
                            "style": {
                                "en_US": ""
                            },
                            "tip": {
                                "en_US": ""
                            },
                            "dataType": "string",
                            "indexType": "keyword",
                            "localizable": true,
                            "name": "Twitter_Link2",
                            "readOnly": false,
                            "repeatable": false,
                            "required": false,
                            "showLabel": true,
                            "type": "text"
                        },
                        {
                            "label": {
                                "en_US": "Linked in Link2"
                            },
                            "predefinedValue": {
                                "en_US": ""
                            },
                            "style": {
                                "en_US": ""
                            },
                            "tip": {
                                "en_US": ""
                            },
                            "dataType": "string",
                            "indexType": "keyword",
                            "localizable": true,
                            "name": "Linked_in_Link2",
                            "readOnly": false,
                            "repeatable": false,
                            "required": false,
                            "showLabel": true,
                            "type": "text"
                        }
                    ]
                },
                {
                    "label": {
                        "en_US": "Show Facebook Link2"
                    },
                    "predefinedValue": {
                        "en_US": false
                    },
                    "style": {
                        "en_US": ""
                    },
                    "tip": {
                        "en_US": ""
                    },
                    "dataType": "boolean",
                    "indexType": "keyword",
                    "localizable": true,
                    "name": "Show_Facebook_Link2",
                    "readOnly": false,
                    "repeatable": false,
                    "required": false,
                    "showLabel": true,
                    "type": "checkbox"
                },
                {
                    "label": {
                        "en_US": "Show Twitter Link2"
                    },
                    "predefinedValue": {
                        "en_US": false
                    },
                    "style": {
                        "en_US": ""
                    },
                    "tip": {
                        "en_US": ""
                    },
                    "dataType": "boolean",
                    "indexType": "keyword",
                    "localizable": true,
                    "name": "Show_Twitter_Link2",
                    "readOnly": false,
                    "repeatable": false,
                    "required": false,
                    "showLabel": true,
                    "type": "checkbox"
                },
                {
                    "label": {
                        "en_US": "Show Linked in Link2"
                    },
                    "predefinedValue": {
                        "en_US": false
                    },
                    "style": {
                        "en_US": ""
                    },
                    "tip": {
                        "en_US": ""
                    },
                    "dataType": "boolean",
                    "indexType": "keyword",
                    "localizable": true,
                    "name": "Show_Linkedin_Link2",
                    "readOnly": false,
                    "repeatable": false,
                    "required": false,
                    "showLabel": true,
                    "type": "checkbox"
                }
            ]
        },
        {
            "label": {
                "en_US": "Team3"
            },
            "predefinedValue": {
                "en_US": ""
            },
            "style": {
                "en_US": ""
            },
            "tip": {
                "en_US": ""
            },
            "dataType": "string",
            "indexType": "keyword",
            "localizable": true,
            "name": "Team3",
            "readOnly": false,
            "repeatable": false,
            "required": false,
            "showLabel": true,
            "type": "text",
            "nestedFields": [
                {
                    "label": {
                        "en_US": "Image3"
                    },
                    "predefinedValue": {
                        "en_US": ""
                    },
                    "style": {
                        "en_US": ""
                    },
                    "tip": {
                        "en_US": ""
                    },
                    "dataType": "document-library",
                    "fieldNamespace": "ddm",
                    "indexType": "keyword",
                    "localizable": true,
                    "name": "Image3",
                    "readOnly": false,
                    "repeatable": false,
                    "required": false,
                    "showLabel": true,
                    "type": "ddm-documentlibrary"
                },
                {
                    "label": {
                        "en_US": "Job Title3"
                    },
                    "predefinedValue": {
                        "en_US": ""
                    },
                    "style": {
                        "en_US": ""
                    },
                    "tip": {
                        "en_US": ""
                    },
                    "dataType": "string",
                    "indexType": "keyword",
                    "localizable": true,
                    "name": "Job_Title3",
                    "readOnly": false,
                    "repeatable": false,
                    "required": false,
                    "showLabel": true,
                    "type": "text"
                },
                {
                    "label": {
                        "en_US": "Job Description3"
                    },
                    "predefinedValue": {
                        "en_US": ""
                    },
                    "style": {
                        "en_US": ""
                    },
                    "tip": {
                        "en_US": ""
                    },
                    "dataType": "string",
                    "indexType": "keyword",
                    "localizable": true,
                    "name": "Job_Description3",
                    "readOnly": false,
                    "repeatable": false,
                    "required": false,
                    "showLabel": true,
                    "type": "textarea",
                    "nestedFields": [
                        {
                            "label": {
                                "en_US": "Facebook Link3"
                            },
                            "predefinedValue": {
                                "en_US": ""
                            },
                            "style": {
                                "en_US": ""
                            },
                            "tip": {
                                "en_US": ""
                            },
                            "dataType": "string",
                            "indexType": "keyword",
                            "localizable": true,
                            "name": "Facebook_Link3",
                            "readOnly": false,
                            "repeatable": false,
                            "required": false,
                            "showLabel": true,
                            "type": "text"
                        },
                        {
                            "label": {
                                "en_US": "Twitter Link3"
                            },
                            "predefinedValue": {
                                "en_US": ""
                            },
                            "style": {
                                "en_US": ""
                            },
                            "tip": {
                                "en_US": ""
                            },
                            "dataType": "string",
                            "indexType": "keyword",
                            "localizable": true,
                            "name": "Twitter_Link3",
                            "readOnly": false,
                            "repeatable": false,
                            "required": false,
                            "showLabel": true,
                            "type": "text"
                        },
                        {
                            "label": {
                                "en_US": "Linked in Link3"
                            },
                            "predefinedValue": {
                                "en_US": ""
                            },
                            "style": {
                                "en_US": ""
                            },
                            "tip": {
                                "en_US": ""
                            },
                            "dataType": "string",
                            "indexType": "keyword",
                            "localizable": true,
                            "name": "Linked_in_Link3",
                            "readOnly": false,
                            "repeatable": false,
                            "required": false,
                            "showLabel": true,
                            "type": "text"
                        }
                    ]
                },
                {
                    "label": {
                        "en_US": "Show Facebook Link3"
                    },
                    "predefinedValue": {
                        "en_US": false
                    },
                    "style": {
                        "en_US": ""
                    },
                    "tip": {
                        "en_US": ""
                    },
                    "dataType": "boolean",
                    "indexType": "keyword",
                    "localizable": true,
                    "name": "Show_Facebook_Link3",
                    "readOnly": false,
                    "repeatable": false,
                    "required": false,
                    "showLabel": true,
                    "type": "checkbox"
                },
                {
                    "label": {
                        "en_US": "Show Twitter Link3"
                    },
                    "predefinedValue": {
                        "en_US": false
                    },
                    "style": {
                        "en_US": ""
                    },
                    "tip": {
                        "en_US": ""
                    },
                    "dataType": "boolean",
                    "indexType": "keyword",
                    "localizable": true,
                    "name": "Show_Twitter_Link3",
                    "readOnly": false,
                    "repeatable": false,
                    "required": false,
                    "showLabel": true,
                    "type": "checkbox"
                },
                {
                    "label": {
                        "en_US": "Show Linked in Link3"
                    },
                    "predefinedValue": {
                        "en_US": false
                    },
                    "style": {
                        "en_US": ""
                    },
                    "tip": {
                        "en_US": ""
                    },
                    "dataType": "boolean",
                    "indexType": "keyword",
                    "localizable": true,
                    "name": "Show_Linkedin_Link3",
                    "readOnly": false,
                    "repeatable": false,
                    "required": false,
                    "showLabel": true,
                    "type": "checkbox"
                }
            ]
        },
        {
            "label": {
                "en_US": "About Us"
            },
            "predefinedValue": {
                "en_US": ""
            },
            "style": {
                "en_US": ""
            },
            "tip": {
                "en_US": ""
            },
            "dataType": "html",
            "fieldNamespace": "ddm",
            "indexType": "keyword",
            "localizable": true,
            "name": "About_Us",
            "readOnly": false,
            "repeatable": false,
            "required": false,
            "showLabel": true,
            "type": "ddm-text-html"
        },
        {
            "label": {
                "en_US": "Hiring"
            },
            "predefinedValue": {
                "en_US": ""
            },
            "style": {
                "en_US": ""
            },
            "tip": {
                "en_US": ""
            },
            "dataType": "string",
            "indexType": "keyword",
            "localizable": true,
            "name": "Hiring",
            "readOnly": false,
            "repeatable": false,
            "required": false,
            "showLabel": true,
            "type": "text",
            "nestedFields": [
                {
                    "label": {
                        "en_US": "Hiring Description"
                    },
                    "predefinedValue": {
                        "en_US": ""
                    },
                    "style": {
                        "en_US": ""
                    },
                    "tip": {
                        "en_US": ""
                    },
                    "dataType": "string",
                    "indexType": "keyword",
                    "localizable": true,
                    "name": "Hiring_Description",
                    "readOnly": false,
                    "repeatable": false,
                    "required": false,
                    "showLabel": true,
                    "type": "textarea"
                },
                {
                    "label": {
                        "en_US": "Hiring Link"
                    },
                    "predefinedValue": {
                        "en_US": ""
                    },
                    "style": {
                        "en_US": ""
                    },
                    "tip": {
                        "en_US": ""
                    },
                    "dataType": "link-to-page",
                    "fieldNamespace": "ddm",
                    "indexType": "keyword",
                    "localizable": true,
                    "name": "Link",
                    "readOnly": false,
                    "repeatable": false,
                    "required": false,
                    "showLabel": true,
                    "type": "ddm-link-to-page"
                }
            ]
        }
    ]
}